README.rst
setup.py
pynguino/__init__.py
pynguino/base.py
pynguino/pcdc.py
pynguino/ptools.py
pynguino/pusb.py
pynguino.egg-info/PKG-INFO
pynguino.egg-info/SOURCES.txt
pynguino.egg-info/dependency_links.txt
pynguino.egg-info/top_level.txt