Metadata-Version: 1.1
Name: pynguino
Version: 2.0.12
Summary: Easy interface Pinguino-Python
Home-page: https://bitbucket.org/YeisonEng/pynguino-2.0
Author: Yeison Cardona
Author-email: yeison.eng@gmail.com
License: BSD 3-Clause
Download-URL: https://bitbucket.org/YeisonEng/pynguino-2.0/downloads
Keywords: microchip,electronic,pinguino
Platform: UNKNOWN
Classifier: Development Status :: 4 - Beta
Classifier: Intended Audience :: Developers
Classifier: License :: OSI Approved :: BSD License
Classifier: Programming Language :: Python
Classifier: Topic :: Scientific/Engineering
Classifier: Topic :: Software Development :: Libraries
